wehavecdathome.py
wehavecdathome-0.0.1.dist-info/METADATA
wehavecdathome-0.0.1.dist-info/WHEEL
wehavecdathome-0.0.1.dist-info/licenses/LICENSE
wehavecdathome-0.0.1.dist-info/RECORD
