Metadata-Version: 2.4
Name: wehavecdathome
Version: 0.0.1
Summary: Quickly set up non production Continuous Delivery using Docker Compose
Project-URL: Homepage, https://github.com/Isaak-Malers/wehavecdathome
Project-URL: Bug Tracker, https://github.com/Isaak-Malers/wehavecdathome/issues
Project-URL: Documentation, https://github.com/Isaak-Malers/wehavecdathome
Author-email: Isaak Malers <isaak.malers+wehavecdathome@gmail.com>
License-File: LICENSE
Classifier: License :: OSI Approved :: MIT License
Classifier: Operating System :: OS Independent
Classifier: Programming Language :: Python :: 3
Requires-Python: >=3.8
